realtime_sge/__init__.py
realtime_sge/master.py
realtime_sge/slave.py
realtime_sge/protos/__init__.py
realtime_sge/protos/messages_pb2.py
realtime_sge/protos/messages_pb2_grpc.py
realtime_sge/protos/services_pb2.py
realtime_sge/protos/services_pb2_grpc.py
realtime_sge_wdroz-0.0.5.dist-info/METADATA
realtime_sge_wdroz-0.0.5.dist-info/WHEEL
realtime_sge_wdroz-0.0.5.dist-info/top_level.txt
realtime_sge_wdroz-0.0.5.dist-info/RECORD
