Metadata-Version: 2.1
Name: realtime-sge-wdroz
Version: 0.0.5
Summary: Internal tools to use the SGE grid in realtime at Idiap Research Institute
Home-page: https://gitlab.idiap.ch/william.droz/realtime_sge
Author: William Droz
Author-email: william.droz@idiap.ch
License: UNKNOWN
Platform: UNKNOWN
Classifier: Programming Language :: Python :: 3
Classifier: License :: OSI Approved :: MIT License
Requires-Python: >=3.5
Requires-Dist: grpcio-tools (>=1.26.0)
Requires-Dist: easy-grid-wdroz (>=0.0.5)
Requires-Dist: psutil (==5.6.3)
